[
  {
    "slug": "rabo-clubkascampagne",
    "title": "Rabo Clubkascampagne",
    "date": "2025-06-23",
    "author": "Buurtvereniging",
    "image": "/clubactie.jpg",
    "excerpt": "Ook dit jaar hebben wij ons ingeschreven voor de Rabo Clubkascampagne."
  },
  {
    "slug": "rabo-clubsupport",
    "title": "Rabo Clubsupport",
    "date": "2025-02-27",
    "author": "Buurtvereniging",
    "image": "/clubkas2025.jpg",
    "excerpt": "Dankzij jullie stemmen hebben we €208,73 opgehaald met de Rabo Clubsupport."
  }
]